crazyimports/__init__.py
crazyimports/_common.py
crazyimports/_csv.py
crazyimports/_json.py
crazyimports/_pickle.py
crazyimports/_sqlite.py
crazyimports/_toml.py
crazyimports/_yaml.py
crazyimports-0.2.1.dist-info/LICENSE
crazyimports-0.2.1.dist-info/METADATA
crazyimports-0.2.1.dist-info/WHEEL
crazyimports-0.2.1.dist-info/top_level.txt
crazyimports-0.2.1.dist-info/RECORD
