Metadata-Version: 2.1
Name: crazyimports
Version: 0.2.1
Summary: Treat your data as your code
Home-page: https://github.com/mishankov/crazy-imports
Author: Denis Mishankov
Author-email: mishankov@mail.com
Classifier: Programming Language :: Python :: 3.7
Classifier: Programming Language :: Python :: 3.8
Classifier: Programming Language :: Python :: 3.9
Classifier: Programming Language :: Python :: 3.10
Classifier: License :: OSI Approved :: MIT License
Classifier: Operating System :: OS Independent
Requires-Python: >=3.7
License-File: LICENSE
Provides-Extra: toml
Requires-Dist: toml (==0.10.2) ; extra == 'toml'
Provides-Extra: yaml
Requires-Dist: PyYAML (==6.0) ; extra == 'yaml'
